read_first_write_first_memory/example.v
module tb;

	localparam	ADDRESS_WIDTH = 4,
					DATA_WIDTH = 8;

   reg tb_clock;
   reg tb_we;
   reg [ADDRESS_WIDTH-1:0] tb_addr_a, tb_addr_b;
   reg [DATA_WIDTH-1:0]	tb_din;

   wire [DATA_WIDTH-1:0] tb_dout_read_first, tb_dout_write_first, tb_dout_another_write_first; 
   
   
initial begin
	tb_clock = 1;
	forever
		#5 tb_clock = ~tb_clock;
end


integer i = 0, j = 0;

initial begin
$dumpvars(0);
//$dumpvars(0, inst_read_first_memory.ram[0]);
//$dumpvars(0, inst_read_first_memory.ram[1]);
//$dumpvars(0, inst_read_first_memory.ram[2]);
//$dumpvars(0, inst_read_first_memory.ram[3]);
//$dumpvars(0, inst_read_first_memory.ram[4]);
//
//$dumpvars(0, inst_write_first_memory.ram[0]);
//$dumpvars(0, inst_write_first_memory.ram[1]);
//$dumpvars(0, inst_write_first_memory.ram[2]);
//$dumpvars(0, inst_write_first_memory.ram[3]);
//$dumpvars(0, inst_write_first_memory.ram[4]);
tb_we = 0;
tb_addr_a = 0;
tb_addr_b = 0;
tb_din = 0;
#10;
repeat (10)  begin
	repeat (5) @(negedge  tb_clock);
	tb_we = 1;
	i = i + 1;
	j = j + 1;
	tb_din = j;
	tb_addr_a = i;
	tb_addr_b = i;
	
	@(negedge  tb_clock);
	j = j + 1;
	tb_din = j;
end
$finish;
end

write_first_memory #(ADDRESS_WIDTH, DATA_WIDTH) inst_write_first_memory (tb_clock, tb_we, tb_addr_a, tb_addr_b, tb_din, tb_dout_write_first);
read_first_memory #(ADDRESS_WIDTH, DATA_WIDTH) inst_read_first_memory(tb_clock, tb_we, tb_addr_a, tb_addr_b, tb_din, tb_dout_read_first);
another_write_first #(ADDRESS_WIDTH, DATA_WIDTH) inst_draft_memory(tb_clock, tb_we, tb_addr_a, tb_addr_b, tb_din, tb_dout_another_write_first);

endmodule

module write_first_memory
	#(
		parameter	ADDRESS_WIDTH = 8,
					DATA_WIDTH = 8
	)
	(
		input	wire	[0:0]				clock,
		input	wire	[0:0]				we,
		input	wire	[ADDRESS_WIDTH-1:0]	addr_a, addr_b,
		input	wire	[DATA_WIDTH-1:0]	din,
		output	wire		[DATA_WIDTH-1:0]	dout
	);

   reg [DATA_WIDTH-1:0] ram [2**ADDRESS_WIDTH-1:0];
   
   integer i = 0;

   initial begin
   		for(i=0; i < 2**ADDRESS_WIDTH; i=i+1)
   			ram[i] = 100;
   end
   
   always @(posedge clock) begin
   	
      if (we)  // write operation
        ram[addr_a] <= din;
   end
   
   assign dout = ram[addr_b];
   
endmodule

module read_first_memory
	#(
		parameter	ADDRESS_WIDTH = 8,
					DATA_WIDTH = 8
	)
	(
		input	wire	[0:0]				clock,
		input	wire	[0:0]				we,
		input	wire	[ADDRESS_WIDTH-1:0]	addr_a, addr_b,
		input	wire	[DATA_WIDTH-1:0]	din,
		output reg		[DATA_WIDTH-1:0]	dout
	);

   reg [DATA_WIDTH-1:0] ram [2**ADDRESS_WIDTH-1:0];

   integer i = 0;

   initial begin
   		for(i=0; i < 2**ADDRESS_WIDTH; i=i+1)
   			ram[i] = 100;
   end

   always @(posedge clock) begin
      
   	dout <= ram[addr_b];	
      if (we)  // write operation
         ram[addr_a] <= din;
   end

endmodule

module another_write_first
	#(
		parameter	ADDRESS_WIDTH = 8,
					DATA_WIDTH = 8
	)
	(
		input	wire	[0:0]				clock,
		input	wire	[0:0]				we,
		input	wire	[ADDRESS_WIDTH-1:0]	addr_a, addr_b,
		input	wire	[DATA_WIDTH-1:0]	din,
		output wire		[DATA_WIDTH-1:0]	dout
	);

   reg [DATA_WIDTH-1:0] ram [2**ADDRESS_WIDTH-1:0];

   integer i = 0;

   initial begin
   		for(i=0; i < 2**ADDRESS_WIDTH; i=i+1)
   			ram[i] = 100;
   end

   reg [ADDRESS_WIDTH-1:0] addr_b_r;
   
   always@(posedge clock) begin
      addr_b_r <= addr_b;
   end

   always @(posedge clock) begin
      if (we)  // write operation
         ram[addr_a] <= din;
   end

   assign dout = ram[addr_b_r];

endmodule

read_first_write_first_memory/dump.vcd
$date
	Thu Feb  7 14:01:03 2019
$end
$version
	Icarus Verilog
$end
$timescale
	1s
$end
$scope module tb $end
$var wire 8 ! tb_dout_write_first [7:0] $end
$var wire 8 " tb_dout_read_first [7:0] $end
$var wire 8 # tb_dout_another_write_first [7:0] $end
$var reg 4 $ tb_addr_a [3:0] $end
$var reg 4 % tb_addr_b [3:0] $end
$var reg 1 & tb_clock $end
$var reg 8 ' tb_din [7:0] $end
$var reg 1 ( tb_we $end
$var integer 32 ) i [31:0] $end
$var integer 32 * j [31:0] $end
$scope module inst_draft_memory $end
$var wire 4 + addr_a [3:0] $end
$var wire 4 , addr_b [3:0] $end
$var wire 1 & clock $end
$var wire 8 - din [7:0] $end
$var wire 8 . dout [7:0] $end
$var wire 1 ( we $end
$var reg 4 / addr_b_r [3:0] $end
$var integer 32 0 i [31:0] $end
$upscope $end
$scope module inst_read_first_memory $end
$var wire 4 1 addr_a [3:0] $end
$var wire 4 2 addr_b [3:0] $end
$var wire 1 & clock $end
$var wire 8 3 din [7:0] $end
$var wire 1 ( we $end
$var reg 8 4 dout [7:0] $end
$var integer 32 5 i [31:0] $end
$upscope $end
$scope module inst_write_first_memory $end
$var wire 4 6 addr_a [3:0] $end
$var wire 4 7 addr_b [3:0] $end
$var wire 1 & clock $end
$var wire 8 8 din [7:0] $end
$var wire 8 9 dout [7:0] $end
$var wire 1 ( we $end
$var integer 32 : i [31:0] $end
$upscope $end
$upscope $end
$enddefinitions $end
#0
$dumpvars
b10000 :
b1100100 9
b0 8
b0 7
b0 6
b10000 5
b1100100 4
b0 3
b0 2
b0 1
b10000 0
b0 /
b1100100 .
b0 -
b0 ,
b0 +
b0 *
b0 )
0(
b0 '
1&
b0 %
b0 $
b1100100 #
b1100100 "
b1100100 !
$end
#5
0&
#10
1&
#15
0&
#20
1&
#25
0&
#30
1&
#35
0&
#40
1&
#45
0&
#50
1&
#55
b1 %
b1 ,
b1 2
b1 7
b1 $
b1 +
b1 1
b1 6
b1 '
b1 -
b1 3
b1 8
b1 *
b1 )
1(
0&
#60
b1 !
b1 9
b1 #
b1 .
b1 /
1&
#65
b10 '
b10 -
b10 3
b10 8
b10 *
0&
#70
b10 #
b10 .
b1 "
b1 4
b10 !
b10 9
1&
#75
0&
#80
b10 "
b10 4
1&
#85
0&
#90
1&
#95
0&
#100
1&
#105
0&
#110
1&
#115
b1100100 !
b1100100 9
b10 %
b10 ,
b10 2
b10 7
b10 $
b10 +
b10 1
b10 6
b11 '
b11 -
b11 3
b11 8
b11 *
b10 )
0&
#120
b11 !
b11 9
b1100100 "
b1100100 4
b11 #
b11 .
b10 /
1&
#125
b100 '
b100 -
b100 3
b100 8
b100 *
0&
#130
b100 #
b100 .
b11 "
b11 4
b100 !
b100 9
1&
#135
0&
#140
b100 "
b100 4
1&
#145
0&
#150
1&
#155
0&
#160
1&
#165
0&
#170
1&
#175
b1100100 !
b1100100 9
b11 %
b11 ,
b11 2
b11 7
b11 $
b11 +
b11 1
b11 6
b101 '
b101 -
b101 3
b101 8
b101 *
b11 )
0&
#180
b101 !
b101 9
b1100100 "
b1100100 4
b101 #
b101 .
b11 /
1&
#185
b110 '
b110 -
b110 3
b110 8
b110 *
0&
#190
b110 #
b110 .
b101 "
b101 4
b110 !
b110 9
1&
#195
0&
#200
b110 "
b110 4
1&
#205
0&
#210
1&
#215
0&
#220
1&
#225
0&
#230
1&
#235
b1100100 !
b1100100 9
b100 %
b100 ,
b100 2
b100 7
b100 $
b100 +
b100 1
b100 6
b111 '
b111 -
b111 3
b111 8
b111 *
b100 )
0&
#240
b111 !
b111 9
b1100100 "
b1100100 4
b111 #
b111 .
b100 /
1&
#245
b1000 '
b1000 -
b1000 3
b1000 8
b1000 *
0&
#250
b1000 #
b1000 .
b111 "
b111 4
b1000 !
b1000 9
1&
#255
0&
#260
b1000 "
b1000 4
1&
#265
0&
#270
1&
#275
0&
#280
1&
#285
0&
#290
1&
#295
b1100100 !
b1100100 9
b101 %
b101 ,
b101 2
b101 7
b101 $
b101 +
b101 1
b101 6
b1001 '
b1001 -
b1001 3
b1001 8
b1001 *
b101 )
0&
#300
b1001 !
b1001 9
b1100100 "
b1100100 4
b1001 #
b1001 .
b101 /
1&
#305
b1010 '
b1010 -
b1010 3
b1010 8
b1010 *
0&
#310
b1010 #
b1010 .
b1001 "
b1001 4
b1010 !
b1010 9
1&
#315
0&
#320
b1010 "
b1010 4
1&
#325
0&
#330
1&
#335
0&
#340
1&
#345
0&
#350
1&
#355
b1100100 !
b1100100 9
b110 %
b110 ,
b110 2
b110 7
b110 $
b110 +
b110 1
b110 6
b1011 '
b1011 -
b1011 3
b1011 8
b1011 *
b110 )
0&
#360
b1011 !
b1011 9
b1100100 "
b1100100 4
b1011 #
b1011 .
b110 /
1&
#365
b1100 '
b1100 -
b1100 3
b1100 8
b1100 *
0&
#370
b1100 #
b1100 .
b1011 "
b1011 4
b1100 !
b1100 9
1&
#375
0&
#380
b1100 "
b1100 4
1&
#385
0&
#390
1&
#395
0&
#400
1&
#405
0&
#410
1&
#415
b1100100 !
b1100100 9
b111 %
b111 ,
b111 2
b111 7
b111 $
b111 +
b111 1
b111 6
b1101 '
b1101 -
b1101 3
b1101 8
b1101 *
b111 )
0&
#420
b1101 !
b1101 9
b1100100 "
b1100100 4
b1101 #
b1101 .
b111 /
1&
#425
b1110 '
b1110 -
b1110 3
b1110 8
b1110 *
0&
#430
b1110 #
b1110 .
b1101 "
b1101 4
b1110 !
b1110 9
1&
#435
0&
#440
b1110 "
b1110 4
1&
#445
0&
#450
1&
#455
0&
#460
1&
#465
0&
#470
1&
#475
b1100100 !
b1100100 9
b1000 %
b1000 ,
b1000 2
b1000 7
b1000 $
b1000 +
b1000 1
b1000 6
b1111 '
b1111 -
b1111 3
b1111 8
b1111 *
b1000 )
0&
#480
b1111 !
b1111 9
b1100100 "
b1100100 4
b1111 #
b1111 .
b1000 /
1&
#485
b10000 '
b10000 -
b10000 3
b10000 8
b10000 *
0&
#490
b10000 #
b10000 .
b1111 "
b1111 4
b10000 !
b10000 9
1&
#495
0&
#500
b10000 "
b10000 4
1&
#505
0&
#510
1&
#515
0&
#520
1&
#525
0&
#530
1&
#535
b1100100 !
b1100100 9
b1001 %
b1001 ,
b1001 2
b1001 7
b1001 $
b1001 +
b1001 1
b1001 6
b10001 '
b10001 -
b10001 3
b10001 8
b10001 *
b1001 )
0&
#540
b10001 !
b10001 9
b1100100 "
b1100100 4
b10001 #
b10001 .
b1001 /
1&
#545
b10010 '
b10010 -
b10010 3
b10010 8
b10010 *
0&
#550
b10010 #
b10010 .
b10001 "
b10001 4
b10010 !
b10010 9
1&
#555
0&
#560
b10010 "
b10010 4
1&
#565
0&
#570
1&
#575
0&
#580
1&
#585
0&
#590
1&
#595
b1100100 !
b1100100 9
b1010 %
b1010 ,
b1010 2
b1010 7
b1010 $
b1010 +
b1010 1
b1010 6
b10011 '
b10011 -
b10011 3
b10011 8
b10011 *
b1010 )
0&
#600
b10011 !
b10011 9
b1100100 "
b1100100 4
b10011 #
b10011 .
b1010 /
1&
#605
b10100 '
b10100 -
b10100 3
b10100 8
b10100 *
0&
